README.md
result_dir.py
setup.py
result_dir.egg-info/PKG-INFO
result_dir.egg-info/SOURCES.txt
result_dir.egg-info/dependency_links.txt
result_dir.egg-info/top_level.txt