Metadata-Version: 2.1
Name: result-dir
Version: 0.0.1
Summary: 一个可复用生物信息流程结果目录结构
Home-page: https://github.com/htbioinfo/result_dir
Author: htbioinfo
Author-email: htbioinfo@gmail.com
License: MIT
Classifier: License :: OSI Approved :: MIT License
Classifier: Programming Language :: Python
Classifier: Programming Language :: Python :: 3
Classifier: Programming Language :: Python :: 3.6
Classifier: Programming Language :: Python :: Implementation :: CPython
Classifier: Programming Language :: Python :: Implementation :: PyPy
Classifier: Topic :: Scientific/Engineering :: Bio-Informatics
Requires-Python: >=3.6.0
